mcpstack_urbanmapper-0.0.1.dist-info/METADATA
mcpstack_urbanmapper-0.0.1.dist-info/WHEEL
mcpstack_urbanmapper-0.0.1.dist-info/entry_points.txt
mcpstack_urbanmapper-0.0.1.dist-info/licenses/LICENSE
mcpstack_urbanmapper/__init__.py
mcpstack_urbanmapper/actions/__init__.py
mcpstack_urbanmapper/actions/discovery.py
mcpstack_urbanmapper/actions/examples.py
mcpstack_urbanmapper/actions/hf.py
mcpstack_urbanmapper/actions/pipeline.py
mcpstack_urbanmapper/actions/shared.py
mcpstack_urbanmapper/actions/visualiser.py
mcpstack_urbanmapper/cli.py
mcpstack_urbanmapper/contexts/__init__.py
mcpstack_urbanmapper/contexts/um_contexts.yaml
mcpstack_urbanmapper/tool.py
mcpstack_urbanmapper-0.0.1.dist-info/RECORD
