Metadata-Version: 2.4
Name: mcpstack-urbanmapper
Version: 0.0.1
Summary: MCPStack tool for UrbanMapper that emits HF-only pipeline code strings (no execution).
Keywords: mcp,mcpstack,mcpPipeline,tool,urbanmapper,huggingface,geospatial,OSCUR,NYU
Author-Email: Provost Simon <s.g.provost@kent.ac.uk>
License-Expression: MIT
Requires-Python: >=3.10
Requires-Dist: typer>=0.9.0
Requires-Dist: beartype>=0.21.0
Requires-Dist: rich>=13.0.0
Requires-Dist: rich-argparse>=1.4.0
Requires-Dist: rich-pyfiglet>=1.0.0
Requires-Dist: click>=8.1.8
Requires-Dist: mcpstack>=0.0.2
Requires-Dist: datasets>=2.20.0
Requires-Dist: urban-mapper==0.1.4
Requires-Dist: pydantic>=2.6.0
Requires-Dist: jsonschema>=4.22.0
Requires-Dist: seaborn>=0.13.2
Requires-Dist: folium>=0.20.0
Requires-Dist: plotly>=6.3.0
Requires-Dist: pandas>=2.3.2
